Metadata-Version: 2.4
Name: domino-py-iisas
Version: 1.0.23
Summary: Fork of the original Python package for Domino.
Author-email: Stefan Dlugolinsky <stefan.dlugolinsky@savba.sk>, Luiz Tauffer <luiz@taufferconsulting.com>, Vinicius Vaz <vinicius@taufferconsulting.com>
License: 
Project-URL: homepage, https://github.com/IISAS/domino
Project-URL: documentation, https://tauffer-consulting.github.io/domino-docs/
Project-URL: repository, https://github.com/IISAS/domino
Keywords: domino,airflow,gui
Classifier: Development Status :: 4 - Beta
Classifier: Programming Language :: Python :: 3
Classifier: Topic :: Scientific/Engineering
Classifier: Topic :: Software Development :: Libraries :: Python Modules
Classifier: Topic :: Software Development :: User Interfaces
Requires-Python: >=3.11
License-File: LICENSE
Requires-Dist: pydantic==2.11.7
Requires-Dist: tomli==2.0.1
Requires-Dist: tomli-w==1.0.0
Requires-Dist: PyYAML==6.0.2
Requires-Dist: jsonschema==4.25.1
Requires-Dist: click==8.2.1
Requires-Dist: rich==13.9.4
Requires-Dist: colorama==0.4.6
Provides-Extra: cli
Requires-Dist: urllib3==2.5.0; extra == "cli"
Requires-Dist: cryptography==45.0.7; extra == "cli"
Requires-Dist: pyOpenSSL==25.1.0; extra == "cli"
Requires-Dist: PyGithub==1.59.1; extra == "cli"
Requires-Dist: docker==7.1.0; extra == "cli"
Requires-Dist: kubernetes==32.0.1; extra == "cli"
Requires-Dist: bottle==0.13.4; extra == "cli"
Requires-Dist: requests==2.32.5; extra == "cli"
Provides-Extra: airflow
Requires-Dist: apache-airflow==3.0.6; extra == "airflow"
Requires-Dist: apache-airflow-providers-cncf-kubernetes==10.7.0; extra == "airflow"
Requires-Dist: apache-airflow-providers-docker==4.4.2; extra == "airflow"
Provides-Extra: full
Requires-Dist: bottle==0.13.4; extra == "full"
Requires-Dist: urllib3==2.5.0; extra == "full"
Requires-Dist: cryptography==45.0.7; extra == "full"
Requires-Dist: pyOpenSSL==25.1.0; extra == "full"
Requires-Dist: PyGithub==1.59.1; extra == "full"
Requires-Dist: docker==7.1.0; extra == "full"
Requires-Dist: kubernetes==32.0.1; extra == "full"
Requires-Dist: apache-airflow==3.0.6; extra == "full"
Requires-Dist: apache-airflow-providers-cncf-kubernetes==10.7.0; extra == "full"
Requires-Dist: apache-airflow-providers-docker==4.4.2; extra == "full"
Dynamic: license-file
